pwv_kpno/__init__.py
pwv_kpno/_download_pwv_data.py
pwv_kpno/_update_pwv_model.py
pwv_kpno/blackbody_with_atm.py
pwv_kpno/exceptions.py
pwv_kpno/package_settings.py
pwv_kpno/pwv_atm.py
pwv_kpno/default_atmosphere/h2ocs.txt
pwv_kpno/default_atmosphere/o2cs.txt
pwv_kpno/default_atmosphere/o3cs.txt
pwv_kpno/site_data/kitt_peak/atm_model.csv
pwv_kpno/site_data/kitt_peak/config.json
pwv_kpno/site_data/kitt_peak/measured_pwv.csv
pwv_kpno/site_data/kitt_peak/modeled_pwv.csv
pwv_kpno/suomi_data/AZAMdy_2012.plt
pwv_kpno/suomi_data/AZAMdy_2013.plt
pwv_kpno/suomi_data/AZAMdy_2014.plt
pwv_kpno/suomi_data/AZAMdy_2015.plt
pwv_kpno/suomi_data/AZAMdy_2016.plt
pwv_kpno/suomi_data/AZAMdy_2017.plt
pwv_kpno/suomi_data/AZAMdy_2018.plt
pwv_kpno/suomi_data/AZAMdy_2019.plt
pwv_kpno/suomi_data/AZAMhr_2012.plt
pwv_kpno/suomi_data/AZAMhr_2013.plt
pwv_kpno/suomi_data/AZAMhr_2014.plt
pwv_kpno/suomi_data/AZAMhr_2015.plt
pwv_kpno/suomi_data/AZAMhr_2016.plt
pwv_kpno/suomi_data/AZAMhr_2017.plt
pwv_kpno/suomi_data/AZAMhr_2018.plt
pwv_kpno/suomi_data/KITTdy_2015.plt
pwv_kpno/suomi_data/KITTdy_2016.plt
pwv_kpno/suomi_data/KITTdy_2017.plt
pwv_kpno/suomi_data/KITTdy_2018.plt
pwv_kpno/suomi_data/KITTdy_2019.plt
pwv_kpno/suomi_data/KITThr_2015.plt
pwv_kpno/suomi_data/KITThr_2016.plt
pwv_kpno/suomi_data/KITThr_2017.plt
pwv_kpno/suomi_data/KITThr_2018.plt
pwv_kpno/suomi_data/P014dy_2010.plt
pwv_kpno/suomi_data/P014dy_2011.plt
pwv_kpno/suomi_data/P014dy_2012.plt
pwv_kpno/suomi_data/P014dy_2013.plt
pwv_kpno/suomi_data/P014dy_2014.plt
pwv_kpno/suomi_data/P014dy_2015.plt
pwv_kpno/suomi_data/P014dy_2016.plt
pwv_kpno/suomi_data/P014dy_2017.plt
pwv_kpno/suomi_data/P014dy_2018.plt
pwv_kpno/suomi_data/P014dy_2019.plt
pwv_kpno/suomi_data/P014hr_2010.plt
pwv_kpno/suomi_data/P014hr_2011.plt
pwv_kpno/suomi_data/P014hr_2012.plt
pwv_kpno/suomi_data/P014hr_2013.plt
pwv_kpno/suomi_data/P014hr_2014.plt
pwv_kpno/suomi_data/P014hr_2015.plt
pwv_kpno/suomi_data/P014hr_2016.plt
pwv_kpno/suomi_data/P014hr_2017.plt
pwv_kpno-1.3.0.dist-info/LICENSE.txt
pwv_kpno-1.3.0.dist-info/METADATA
pwv_kpno-1.3.0.dist-info/WHEEL
pwv_kpno-1.3.0.dist-info/top_level.txt
pwv_kpno-1.3.0.dist-info/RECORD
