Metadata-Version: 2.1
Name: pwv-kpno
Version: 1.3.0
Summary: Models the atmospheric transmission function for KPNO
Home-page: https://mwvgroup.github.io/pwv_kpno/
Author: Daniel Perrefort
Author-email: djperrefort@pitt.edu
License: GPL v3
Keywords: KPNO atmospheric transmission PWV precipitable water vapor
Classifier: Development Status :: 4 - Beta
Classifier: Intended Audience :: Science/Research
Classifier: License :: OSI Approved :: GNU General Public License v3 or later (GPLv3+)
Classifier: Natural Language :: English
Classifier: Operating System :: OS Independent
Classifier: Programming Language :: Python
Classifier: Programming Language :: Python :: 3
Classifier: Topic :: Scientific/Engineering :: Astronomy
Classifier: Topic :: Scientific/Engineering :: Atmospheric Science
Classifier: Topic :: Scientific/Engineering :: Physics
Requires-Python: >=3.6
License-File: LICENSE.txt
Requires-Dist: numpy >=1.17.0
Requires-Dist: astropy >=3.0.0
Requires-Dist: requests
Requires-Dist: pytz
Requires-Dist: scipy
